{
	"info": {
		"_postman_id": "f1c792c2-cf36-4d91-b87b-92bce749795e",
		"name": "CONVERGÊNCIA - CPF",
		"schema": "https://schema.getpostman.com/json/collection/v2.1.0/collection.json"
	},
	"item": [
		{
			"name": "CREATE",
			"request": {
				"method": "POST",
				"header": [],
				"body": {
					"mode": "raw",
					"raw": "{\n    \"number\" : \"023.704.531-17\"\n}",
					"options": {
						"raw": {
							"language": "json"
						}
					}
				},
				"url": {
					"raw": "http://localhost:8080/convergencia/v1/cpfs",
					"protocol": "http",
					"host": [
						"localhost"
					],
					"port": "8080",
					"path": [
						"convergencia",
						"v1",
						"cpfs"
					]
				}
			},
			"response": []
		},
		{
			"name": "UPDATE",
			"request": {
				"method": "PATCH",
				"header": [],
				"body": {
					"mode": "raw",
					"raw": "{\n    \"status\" : \"INACTIVE\"\n}",
					"options": {
						"raw": {
							"language": "json"
						}
					}
				},
				"url": {
					"raw": "http://localhost:8080/convergencia/v1/cpfs/023.704.531-17",
					"protocol": "http",
					"host": [
						"localhost"
					],
					"port": "8080",
					"path": [
						"convergencia",
						"v1",
						"cpfs",
						"023.704.531-17"
					]
				}
			},
			"response": []
		},
		{
			"name": "READ",
			"request": {
				"method": "GET",
				"header": [],
				"url": {
					"raw": "http://localhost:8080/convergencia/v1/cpfs/023.704.531-17",
					"protocol": "http",
					"host": [
						"localhost"
					],
					"port": "8080",
					"path": [
						"convergencia",
						"v1",
						"cpfs",
						"023.704.531-17"
					]
				}
			},
			"response": []
		}
	]
}